kivymd_akivymd_sylvia_dynamic/__init__.py
kivymd_akivymd_sylvia_dynamic/icont/Pollywog.ttf
kivymd_akivymd_sylvia_dynamic/icont/fontello.fontd
kivymd_akivymd_sylvia_dynamic/icont/fontello.ttf
kivymd_akivymd_sylvia_dynamic/icont/icomoon.fontd
kivymd_akivymd_sylvia_dynamic/icont/icomoon.ttf
kivymd_akivymd_sylvia_dynamic/icont/icomoon2.fontd
kivymd_akivymd_sylvia_dynamic/icont/icomoon2.ttf
kivymd_akivymd_sylvia_dynamic/icont/ua_scroonge.ttf
kivymd_akivymd_sylvia_dynamic/tools/iconfonts.py
kivymd_akivymd_sylvia_dynamic/uix/__init__.py
kivymd_akivymd_sylvia_dynamic/uix/a_bottomnavigation.py
kivymd_akivymd_sylvia_dynamic/uix/a_silverappbar.py
kivymd_akivymd_sylvia_dynamic/uix/card.py
kivymd_akivymd_sylvia_dynamic/uix/fitimage.py
kivymd_akivymd_sylvia_dynamic/uix/fitimages.py
kivymd_akivymd_sylvia_dynamic/uix/m_mdbuttons.py
kivymd_akivymd_sylvia_dynamic/uix/managerswiper.py
kivymd_akivymd_sylvia_dynamic/uix/roundedfitimage.py
KivyMD_AKivymd_Sylvia_Dynamic-0.1.1.dist-info/LICENSE
KivyMD_AKivymd_Sylvia_Dynamic-0.1.1.dist-info/METADATA
KivyMD_AKivymd_Sylvia_Dynamic-0.1.1.dist-info/WHEEL
KivyMD_AKivymd_Sylvia_Dynamic-0.1.1.dist-info/top_level.txt
KivyMD_AKivymd_Sylvia_Dynamic-0.1.1.dist-info/RECORD
